touca_fbs/__init__.py
touca_fbs/py.typed
touca_fbs-0.0.3.dist-info/WHEEL
touca_fbs-0.0.3.dist-info/METADATA
touca_fbs-0.0.3.dist-info/RECORD
